d_08/__init__.py
d_08/asgi.py
d_08/settings.py
d_08/urls.py
d_08/wsgi.py
ex/__init__.py
ex/admin.py
ex/apps.py
ex/forms.py
ex/models.py
ex/tests.py
ex/urls.py
ex/views.py
ex/migrations/0001_initial.py
ex/migrations/__init__.py
django_d08-0.1.dist-info/METADATA
django_d08-0.1.dist-info/WHEEL
django_d08-0.1.dist-info/top_level.txt
django_d08-0.1.dist-info/RECORD
